card_gen_package/__init__.py
card_gen_package/generate.py
card_gen-0.1.0.dist-info/METADATA
card_gen-0.1.0.dist-info/WHEEL
card_gen-0.1.0.dist-info/top_level.txt
card_gen-0.1.0.dist-info/RECORD
