Metadata-Version: 2.4
Name: card_gen
Version: 0.1.0
Summary: A simple package to generate annotated images with text and logo.
Author: Tapas Pradhan
Author-email: tapas.pradhan1801@gmail.com
Requires-Python: >=3.8
Requires-Dist: Pillow>=10.0.0
Dynamic: author
Dynamic: author-email
Dynamic: requires-dist
Dynamic: requires-python
Dynamic: summary
